README.md
setup.py
ECSMetrics/__init__.py
ECSMetrics/__main__.py
ECSMetrics/awsecs.py
ECSMetrics/expdict.py
ECSMetrics/operations.py
ecs_metrics.egg-info/PKG-INFO
ecs_metrics.egg-info/SOURCES.txt
ecs_metrics.egg-info/dependency_links.txt
ecs_metrics.egg-info/entry_points.txt
ecs_metrics.egg-info/requires.txt
ecs_metrics.egg-info/top_level.txt